{
  "input": {
    "handle": "odad-im-a-f-cking-unicorn",
    "title": "I'm a F*cking Unicorn",
    "vendor": "ducfrench",
    "productType": "ODAD",
    "options": ["Gender", "Size", "Color"],
    "tags": [
      "artist-ducfrench",
      "color-Black",
      "color-Royal Blue",
      "ducfrench",
      "gender-Men",
      "gender-Men Premium",
      "gender-Women",
      "gender-Womens Fitted",
      "gender-Youth",
      "odad-2019-11-17",
      "odad-2019-11-18",
      "odad-design-d2",
      "product-type-Tees",
      "size-2xl",
      "size-3xl",
      "size-l",
      "size-m",
      "size-s",
      "size-xl",
      "size-xs",
      "teefury",
      "Tees"
    ],
    "metafields": [
      {
        "namespace": "global",
        "key": "description_tag",
        "value": "I'm a F*cking Unicorn - Tees - by ducfrench",
        "valueType": "STRING",
        "description": null
      },
      {
        "namespace": "global",
        "key": "printfile_URL",
        "value": "http://printfiles.teefury.com/PrintFiles/I-Artwork/production_im-a-fcking-unicorn_ducfrench.png",
        "valueType": "STRING",
        "description": null
      },
      {
        "namespace": "global",
        "key": "small_image",
        "value": "https://storage.googleapis.com/torrid-inferno-3935.appspot.com/artwork%2FokNRdYBimVwcz1D9Mqol-R7EzcKd9ftUycaF9kz6a-y1ayM0MLtH693S4GPYr1-color-none.png?GoogleAccessId=torrid-inferno-3935%40appspot.gserviceaccount.com\u0026Expires=16730323200\u0026Signature=TVZo%2F29SS4ZTv35JGPgl9CWKhuY7v6ij5mf9NzLN1y1uoypxVPDuyVmVfObUoTpBp0FGcHvXFOxQNafmYeLyuCbCLxeUzNPNtkKNyIRTThFRYu04OaapLcAsb4mqJ0g686vBAHL2hUHc9SG%2FCY1P8Asht8gIG8oV4G7ZssfgyMrpUPHmIlw1MAR4GUue7GJBmBaMBH47%2B1N2BGV2Ei3ZJs%2BHoF%2BwcIEK5y7eJETXScxsUww4JunvpL3Kfjnxqk%2Btmst%2F9u%2B9xxByPFGaRmPdaye%2FFxvle0T08tilaJVbKD1fCa2CkbawzDE8u3ZjxfZRjccEJj0AjNpkX72ay91RMg%3D%3D",
        "valueType": "STRING",
        "description": null
      },
      {
        "namespace": "global",
        "key": "title_tag",
        "value": "I'm a F*cking Unicorn - Tees - by ducfrench",
        "valueType": "STRING",
        "description": null
      },
      {
        "namespace": "odad",
        "key": "odadartfile",
        "value": "https://firebasestorage.googleapis.com/v0/b/torrid-inferno-3935.appspot.com/o/artwork%2Ffinal_iolulzrmev69pimi8r7o-color-%23000000.png?alt=media\u0026token=6c3a4030-de7a-4419-9b94-7da5c58686ae",
        "valueType": "STRING",
        "description": null
      },
      {
        "namespace": "odad",
        "key": "odadflat",
        "value": "https://firebasestorage.googleapis.com/v0/b/torrid-inferno-3935.appspot.com/o/artwork%2Ffinal_sonvjubji2aulvkhrmgt-color-%23000000.png?alt=media\u0026token=884c7aa8-cf6f-46e3-8a1c-20e69934535d",
        "valueType": "STRING",
        "description": null
      },
      {
        "namespace": "odad",
        "key": "odadmodel",
        "value": "https://firebasestorage.googleapis.com/v0/b/torrid-inferno-3935.appspot.com/o/artwork%2Ffinal_iplvcotzqrnvpzdjxmez-color-%23000000.png?alt=media\u0026token=d7af7a5e-bb7f-4d6f-afd6-9acd5bb41cb3",
        "valueType": "STRING",
        "description": null
      },
      {
        "namespace": "teefuryapp",
        "key": "artwork_id",
        "value": "okNRdYBimVwcz1D9Mqol",
        "valueType": "STRING",
        "description": null
      },
      {
        "namespace": "teefuryapp",
        "key": "colors",
        "value": "#3145B6,#000000,none,none",
        "valueType": "STRING",
        "description": null
      },
      {
        "namespace": "teefuryapp",
        "key": "product_id",
        "value": "R7EzcKd9ftUycaF9kz6a",
        "valueType": "STRING",
        "description": null
      }
    ],
    "images": [
      {
        "src": "https://cdn.shopify.com/s/files/1/1869/0319/products/artwork_2FokNRdYBimVwcz1D9Mqol-R7EzcKd9ftUycaF9kz6a-uVf7CLkzDgl9b9IjbZuD-color-none.png?v=1573687790"
      },
      {
        "src": "https://cdn.shopify.com/s/files/1/1869/0319/products/ART-im-a-f-cking-unicorn_ducfrench_color-black.jpg?v=1573688041"
      },
      {
        "src": "https://cdn.shopify.com/s/files/1/1869/0319/products/ART-im-a-f-cking-unicorn_ducfrench_color-royal-blue.jpg?v=1573688041"
      }
    ],
    "variants": [
      {
        "title": "Men / S / Black",
        "price": "12.00",
        "sku": "4355103686722-tee-men-bla-s",
        "inventoryPolicy": "DENY",
        "inventoryItem": { "tracked": false },
        "options": [ "Men", "S", "Black"],
        "weight": 0.3625,
        "weightUnit": "POUNDS",
        "requiresShipping": true,
        "imageSrc": "https://cdn.shopify.com/s/files/1/1869/0319/products/artwork_2FokNRdYBimVwcz1D9Mqol-R7EzcKd9ftUycaF9kz6a-uVf7CLkzDgl9b9IjbZuD-color-none.png?v=1573687790"
      },
      {
        "title": "Men / M / Black",
        "price": "12.00",
        "sku": "4355103686722-tee-men-bla-m",
        "inventoryPolicy": "DENY",
        "inventoryItem": { "tracked": false },
        "options": [ "Men", "M", "Black"],
        "weight": 0.4125,
        "weightUnit": "POUNDS",
        "requiresShipping": true,
        "imageSrc": "https://cdn.shopify.com/s/files/1/1869/0319/products/artwork_2FokNRdYBimVwcz1D9Mqol-R7EzcKd9ftUycaF9kz6a-uVf7CLkzDgl9b9IjbZuD-color-none.png?v=1573687790"
      },
      {
        "title": "Men / L / Black",
        "price": "12.00",
        "sku": "4355103686722-tee-men-bla-l",
        "inventoryPolicy": "DENY",
        "inventoryItem": { "tracked": false },
        "options": [ "Men", "L", "Black"],
        "weight": 0.5125,
        "weightUnit": "POUNDS",
        "requiresShipping": true,
        "imageSrc": "https://cdn.shopify.com/s/files/1/1869/0319/products/artwork_2FokNRdYBimVwcz1D9Mqol-R7EzcKd9ftUycaF9kz6a-uVf7CLkzDgl9b9IjbZuD-color-none.png?v=1573687790"
      },
      {
        "title": "Men / XL / Black",
        "price": "12.00",
        "sku": "4355103686722-tee-men-bla-xl",
        "inventoryPolicy": "DENY",
        "inventoryItem": { "tracked": false },
        "options": [ "Men", "XL", "Black"],
        "weight": 0.5225,
        "weightUnit": "POUNDS",
        "requiresShipping": true,
        "imageSrc": "https://cdn.shopify.com/s/files/1/1869/0319/products/artwork_2FokNRdYBimVwcz1D9Mqol-R7EzcKd9ftUycaF9kz6a-uVf7CLkzDgl9b9IjbZuD-color-none.png?v=1573687790"
      },
      {
        "title": "Men / 2XL / Black",
        "price": "13.00",
        "sku": "4355103686722-tee-men-bla-2xl",
        "inventoryPolicy": "DENY",
        "inventoryItem": { "tracked": false },
        "options": [ "Men", "2XL", "Black"],
        "weight": 0.6125,
        "weightUnit": "POUNDS",
        "requiresShipping": true,
        "imageSrc": "https://cdn.shopify.com/s/files/1/1869/0319/products/artwork_2FokNRdYBimVwcz1D9Mqol-R7EzcKd9ftUycaF9kz6a-uVf7CLkzDgl9b9IjbZuD-color-none.png?v=1573687790"
      },
      {
        "title": "Men / 3XL / Black",
        "price": "14.00",
        "sku": "4355103686722-tee-men-bla-3xl",
        "inventoryPolicy": "DENY",
        "inventoryItem": { "tracked": false },
        "options": [ "Men", "3XL", "Black"],
        "weight": 0.6525,
        "weightUnit": "POUNDS",
        "requiresShipping": true,
        "imageSrc": "https://cdn.shopify.com/s/files/1/1869/0319/products/artwork_2FokNRdYBimVwcz1D9Mqol-R7EzcKd9ftUycaF9kz6a-uVf7CLkzDgl9b9IjbZuD-color-none.png?v=1573687790"
      },
      {
        "title": "Men / S / Royal Blue",
        "price": "12.00",
        "sku": "4355103686722-tee-men-robl-s",
        "inventoryPolicy": "DENY",
        "inventoryItem": { "tracked": false },
        "options": [ "Men", "S", "Royal Blue"],
        "weight": 0.3625,
        "weightUnit": "POUNDS",
        "requiresShipping": true,
        "imageSrc": "https://cdn.shopify.com/s/files/1/1869/0319/products/artwork_2FokNRdYBimVwcz1D9Mqol-R7EzcKd9ftUycaF9kz6a-uVf7CLkzDgl9b9IjbZuD-color-none.png?v=1573687790"
      },
      {
        "title": "Men / M / Royal Blue",
        "price": "12.00",
        "sku": "4355103686722-tee-men-robl-m",
        "inventoryPolicy": "DENY",
        "inventoryItem": { "tracked": false },
        "options": [ "Men", "M", "Royal Blue"],
        "weight": 0.4125,
        "weightUnit": "POUNDS",
        "requiresShipping": true,
        "imageSrc": "https://cdn.shopify.com/s/files/1/1869/0319/products/artwork_2FokNRdYBimVwcz1D9Mqol-R7EzcKd9ftUycaF9kz6a-uVf7CLkzDgl9b9IjbZuD-color-none.png?v=1573687790"
      },
      {
        "title": "Men / L / Royal Blue",
        "price": "12.00",
        "sku": "4355103686722-tee-men-robl-l",
        "inventoryPolicy": "DENY",
        "inventoryItem": { "tracked": false },
        "options": [ "Men", "L", "Royal Blue"],
        "weight": 0.5125,
        "weightUnit": "POUNDS",
        "requiresShipping": true,
        "imageSrc": "https://cdn.shopify.com/s/files/1/1869/0319/products/artwork_2FokNRdYBimVwcz1D9Mqol-R7EzcKd9ftUycaF9kz6a-uVf7CLkzDgl9b9IjbZuD-color-none.png?v=1573687790"
      },
      {
        "title": "Men / XL / Royal Blue",
        "price": "12.00",
        "sku": "4355103686722-tee-men-robl-xl",
        "inventoryPolicy": "DENY",
        "inventoryItem": { "tracked": false },
        "options": [ "Men", "XL", "Royal Blue"],
        "weight": 0.5225,
        "weightUnit": "POUNDS",
        "requiresShipping": true,
        "imageSrc": "https://cdn.shopify.com/s/files/1/1869/0319/products/artwork_2FokNRdYBimVwcz1D9Mqol-R7EzcKd9ftUycaF9kz6a-uVf7CLkzDgl9b9IjbZuD-color-none.png?v=1573687790"
      },
      {
        "title": "Men / 2XL / Royal Blue",
        "price": "13.00",
        "sku": "4355103686722-tee-men-robl-2xl",
        "inventoryPolicy": "DENY",
        "inventoryItem": { "tracked": false },
        "options": [ "Men", "2XL", "Royal Blue"],
        "weight": 0.6125,
        "weightUnit": "POUNDS",
        "requiresShipping": true,
        "imageSrc": "https://cdn.shopify.com/s/files/1/1869/0319/products/artwork_2FokNRdYBimVwcz1D9Mqol-R7EzcKd9ftUycaF9kz6a-uVf7CLkzDgl9b9IjbZuD-color-none.png?v=1573687790"
      },
      {
        "title": "Men / 3XL / Royal Blue",
        "price": "14.00",
        "sku": "4355103686722-tee-men-robl-3xl",
        "inventoryPolicy": "DENY",
        "inventoryItem": { "tracked": false },
        "options": [ "Men", "3XL", "Royal Blue"],
        "weight": 0.6525,
        "weightUnit": "POUNDS",
        "requiresShipping": true,
        "imageSrc": "https://cdn.shopify.com/s/files/1/1869/0319/products/artwork_2FokNRdYBimVwcz1D9Mqol-R7EzcKd9ftUycaF9kz6a-uVf7CLkzDgl9b9IjbZuD-color-none.png?v=1573687790"
      },
      {
        "title": "Men Premium / S / Black",
        "price": "16.00",
        "sku": "4355103686722-tee-mepr-bla-s",
        "inventoryPolicy": "DENY",
        "inventoryItem": { "tracked": false },
        "options": [ "Men Premium", "S", "Black"],
        "weight": 0.31,
        "weightUnit": "POUNDS",
        "requiresShipping": true,
        "imageSrc": "https://cdn.shopify.com/s/files/1/1869/0319/products/artwork_2FokNRdYBimVwcz1D9Mqol-R7EzcKd9ftUycaF9kz6a-uVf7CLkzDgl9b9IjbZuD-color-none.png?v=1573687790"
      },
      {
        "title": "Men Premium / M / Black",
        "price": "16.00",
        "sku": "4355103686722-tee-mepr-bla-m",
        "inventoryPolicy": "DENY",
        "inventoryItem": { "tracked": false },
        "options": [ "Men Premium", "M", "Black"],
        "weight": 0.34,
        "weightUnit": "POUNDS",
        "requiresShipping": true,
        "imageSrc": "https://cdn.shopify.com/s/files/1/1869/0319/products/artwork_2FokNRdYBimVwcz1D9Mqol-R7EzcKd9ftUycaF9kz6a-uVf7CLkzDgl9b9IjbZuD-color-none.png?v=1573687790"
      },
      {
        "title": "Men Premium / L / Black",
        "price": "16.00",
        "sku": "4355103686722-tee-mepr-bla-l",
        "inventoryPolicy": "DENY",
        "inventoryItem": { "tracked": false },
        "options": [ "Men Premium", "L", "Black"],
        "weight": 0.39,
        "weightUnit": "POUNDS",
        "requiresShipping": true,
        "imageSrc": "https://cdn.shopify.com/s/files/1/1869/0319/products/artwork_2FokNRdYBimVwcz1D9Mqol-R7EzcKd9ftUycaF9kz6a-uVf7CLkzDgl9b9IjbZuD-color-none.png?v=1573687790"
      },
      {
        "title": "Men Premium / XL / Black",
        "price": "16.00",
        "sku": "4355103686722-tee-mepr-bla-xl",
        "inventoryPolicy": "DENY",
        "inventoryItem": { "tracked": false },
        "options": [ "Men Premium", "XL", "Black"],
        "weight": 0.42,
        "weightUnit": "POUNDS",
        "requiresShipping": true,
        "imageSrc": "https://cdn.shopify.com/s/files/1/1869/0319/products/artwork_2FokNRdYBimVwcz1D9Mqol-R7EzcKd9ftUycaF9kz6a-uVf7CLkzDgl9b9IjbZuD-color-none.png?v=1573687790"
      },
      {
        "title": "Men Premium / 2XL / Black",
        "price": "17.00",
        "sku": "4355103686722-tee-mepr-bla-2xl",
        "inventoryPolicy": "DENY",
        "inventoryItem": { "tracked": false },
        "options": [ "Men Premium", "2XL", "Black"],
        "weight": 0.46,
        "weightUnit": "POUNDS",
        "requiresShipping": true,
        "imageSrc": "https://cdn.shopify.com/s/files/1/1869/0319/products/artwork_2FokNRdYBimVwcz1D9Mqol-R7EzcKd9ftUycaF9kz6a-uVf7CLkzDgl9b9IjbZuD-color-none.png?v=1573687790"
      },
      {
        "title": "Men Premium / 3XL / Black",
        "price": "18.00",
        "sku": "4355103686722-tee-mepr-bla-3xl",
        "inventoryPolicy": "DENY",
        "inventoryItem": { "tracked": false },
        "options": [ "Men Premium", "3XL", "Black"],
        "weight": 0.49,
        "weightUnit": "POUNDS",
        "requiresShipping": true,
        "imageSrc": "https://cdn.shopify.com/s/files/1/1869/0319/products/artwork_2FokNRdYBimVwcz1D9Mqol-R7EzcKd9ftUycaF9kz6a-uVf7CLkzDgl9b9IjbZuD-color-none.png?v=1573687790"
      },
      {
        "title": "Men Premium / S / Royal Blue",
        "price": "16.00",
        "sku": "4355103686722-tee-mepr-robl-s",
        "inventoryPolicy": "DENY",
        "inventoryItem": { "tracked": false },
        "options": [ "Men Premium", "S", "Royal Blue"],
        "weight": 0.31,
        "weightUnit": "POUNDS",
        "requiresShipping": true,
        "imageSrc": "https://cdn.shopify.com/s/files/1/1869/0319/products/artwork_2FokNRdYBimVwcz1D9Mqol-R7EzcKd9ftUycaF9kz6a-uVf7CLkzDgl9b9IjbZuD-color-none.png?v=1573687790"
      },
      {
        "title": "Men Premium / M / Royal Blue",
        "price": "16.00",
        "sku": "4355103686722-tee-mepr-robl-m",
        "inventoryPolicy": "DENY",
        "inventoryItem": { "tracked": false },
        "options": [ "Men Premium", "M", "Royal Blue"],
        "weight": 0.34,
        "weightUnit": "POUNDS",
        "requiresShipping": true,
        "imageSrc": "https://cdn.shopify.com/s/files/1/1869/0319/products/artwork_2FokNRdYBimVwcz1D9Mqol-R7EzcKd9ftUycaF9kz6a-uVf7CLkzDgl9b9IjbZuD-color-none.png?v=1573687790"
      },
      {
        "title": "Men Premium / L / Royal Blue",
        "price": "16.00",
        "sku": "4355103686722-tee-mepr-robl-l",
        "inventoryPolicy": "DENY",
        "inventoryItem": { "tracked": false },
        "options": [ "Men Premium", "L", "Royal Blue"],
        "weight": 0.39,
        "weightUnit": "POUNDS",
        "requiresShipping": true,
        "imageSrc": "https://cdn.shopify.com/s/files/1/1869/0319/products/artwork_2FokNRdYBimVwcz1D9Mqol-R7EzcKd9ftUycaF9kz6a-uVf7CLkzDgl9b9IjbZuD-color-none.png?v=1573687790"
      },
      {
        "title": "Men Premium / XL / Royal Blue",
        "price": "16.00",
        "sku": "4355103686722-tee-mepr-robl-xl",
        "inventoryPolicy": "DENY",
        "inventoryItem": { "tracked": false },
        "options": [ "Men Premium", "XL", "Royal Blue"],
        "weight": 0.42,
        "weightUnit": "POUNDS",
        "requiresShipping": true,
        "imageSrc": "https://cdn.shopify.com/s/files/1/1869/0319/products/artwork_2FokNRdYBimVwcz1D9Mqol-R7EzcKd9ftUycaF9kz6a-uVf7CLkzDgl9b9IjbZuD-color-none.png?v=1573687790"
      },
      {
        "title": "Men Premium / 2XL / Royal Blue",
        "price": "17.00",
        "sku": "4355103686722-tee-mepr-robl-2xl",
        "inventoryPolicy": "DENY",
        "inventoryItem": { "tracked": false },
        "options": [ "Men Premium", "2XL", "Royal Blue"],
        "weight": 0.46,
        "weightUnit": "POUNDS",
        "requiresShipping": true,
        "imageSrc": "https://cdn.shopify.com/s/files/1/1869/0319/products/artwork_2FokNRdYBimVwcz1D9Mqol-R7EzcKd9ftUycaF9kz6a-uVf7CLkzDgl9b9IjbZuD-color-none.png?v=1573687790"
      },
      {
        "title": "Men Premium / 3XL / Royal Blue",
        "price": "18.00",
        "sku": "4355103686722-tee-mepr-robl-3xl",
        "inventoryPolicy": "DENY",
        "inventoryItem": { "tracked": false },
        "options": [ "Men Premium", "3XL", "Royal Blue"],
        "weight": 0.49,
        "weightUnit": "POUNDS",
        "requiresShipping": true,
        "imageSrc": "https://cdn.shopify.com/s/files/1/1869/0319/products/artwork_2FokNRdYBimVwcz1D9Mqol-R7EzcKd9ftUycaF9kz6a-uVf7CLkzDgl9b9IjbZuD-color-none.png?v=1573687790"
      },
      {
        "title": "Women / S / Black",
        "price": "12.00",
        "sku": "4355103686722-tee-wom-bla-s",
        "inventoryPolicy": "DENY",
        "inventoryItem": { "tracked": false },
        "options": [ "Women", "S", "Black"],
        "weight": 0.2525,
        "weightUnit": "POUNDS",
        "requiresShipping": true,
        "imageSrc": "https://cdn.shopify.com/s/files/1/1869/0319/products/artwork_2FokNRdYBimVwcz1D9Mqol-R7EzcKd9ftUycaF9kz6a-uVf7CLkzDgl9b9IjbZuD-color-none.png?v=1573687790"
      },
      {
        "title": "Women / M / Black",
        "price": "12.00",
        "sku": "4355103686722-tee-wom-bla-m",
        "inventoryPolicy": "DENY",
        "inventoryItem": { "tracked": false },
        "options": [ "Women", "M", "Black"],
        "weight": 0.2725,
        "weightUnit": "POUNDS",
        "requiresShipping": true,
        "imageSrc": "https://cdn.shopify.com/s/files/1/1869/0319/products/artwork_2FokNRdYBimVwcz1D9Mqol-R7EzcKd9ftUycaF9kz6a-uVf7CLkzDgl9b9IjbZuD-color-none.png?v=1573687790"
      },
      {
        "title": "Women / L / Black",
        "price": "12.00",
        "sku": "4355103686722-tee-wom-bla-l",
        "inventoryPolicy": "DENY",
        "inventoryItem": { "tracked": false },
        "options": [ "Women", "L", "Black"],
        "weight": 0.3125,
        "weightUnit": "POUNDS",
        "requiresShipping": true,
        "imageSrc": "https://cdn.shopify.com/s/files/1/1869/0319/products/artwork_2FokNRdYBimVwcz1D9Mqol-R7EzcKd9ftUycaF9kz6a-uVf7CLkzDgl9b9IjbZuD-color-none.png?v=1573687790"
      },
      {
        "title": "Women / XL / Black",
        "price": "12.00",
        "sku": "4355103686722-tee-wom-bla-xl",
        "inventoryPolicy": "DENY",
        "inventoryItem": { "tracked": false },
        "options": [ "Women", "XL", "Black"],
        "weight": 0.3525,
        "weightUnit": "POUNDS",
        "requiresShipping": true,
        "imageSrc": "https://cdn.shopify.com/s/files/1/1869/0319/products/artwork_2FokNRdYBimVwcz1D9Mqol-R7EzcKd9ftUycaF9kz6a-uVf7CLkzDgl9b9IjbZuD-color-none.png?v=1573687790"
      },
      {
        "title": "Women / 2XL / Black",
        "price": "13.00",
        "sku": "4355103686722-tee-wom-bla-2xl",
        "inventoryPolicy": "DENY",
        "inventoryItem": { "tracked": false },
        "options": [ "Women", "2XL", "Black"],
        "weight": 0.3725,
        "weightUnit": "POUNDS",
        "requiresShipping": true,
        "imageSrc": "https://cdn.shopify.com/s/files/1/1869/0319/products/artwork_2FokNRdYBimVwcz1D9Mqol-R7EzcKd9ftUycaF9kz6a-uVf7CLkzDgl9b9IjbZuD-color-none.png?v=1573687790"
      },
      {
        "title": "Women / 3XL / Black",
        "price": "14.00",
        "sku": "4355103686722-tee-wom-bla-3xl",
        "inventoryPolicy": "DENY",
        "inventoryItem": { "tracked": false },
        "options": [ "Women", "3XL", "Black"],
        "weight": 0.4025,
        "weightUnit": "POUNDS",
        "requiresShipping": true,
        "imageSrc": "https://cdn.shopify.com/s/files/1/1869/0319/products/artwork_2FokNRdYBimVwcz1D9Mqol-R7EzcKd9ftUycaF9kz6a-uVf7CLkzDgl9b9IjbZuD-color-none.png?v=1573687790"
      },
      {
        "title": "Women / S / Royal Blue",
        "price": "12.00",
        "sku": "4355103686722-tee-wom-robl-s",
        "inventoryPolicy": "DENY",
        "inventoryItem": { "tracked": false },
        "options": [ "Women", "S", "Royal Blue"],
        "weight": 0.2525,
        "weightUnit": "POUNDS",
        "requiresShipping": true,
        "imageSrc": "https://cdn.shopify.com/s/files/1/1869/0319/products/artwork_2FokNRdYBimVwcz1D9Mqol-R7EzcKd9ftUycaF9kz6a-uVf7CLkzDgl9b9IjbZuD-color-none.png?v=1573687790"
      },
      {
        "title": "Women / M / Royal Blue",
        "price": "12.00",
        "sku": "4355103686722-tee-wom-robl-m",
        "inventoryPolicy": "DENY",
        "inventoryItem": { "tracked": false },
        "options": [ "Women", "M", "Royal Blue"],
        "weight": 0.2725,
        "weightUnit": "POUNDS",
        "requiresShipping": true,
        "imageSrc": "https://cdn.shopify.com/s/files/1/1869/0319/products/artwork_2FokNRdYBimVwcz1D9Mqol-R7EzcKd9ftUycaF9kz6a-uVf7CLkzDgl9b9IjbZuD-color-none.png?v=1573687790"
      },
      {
        "title": "Women / L / Royal Blue",
        "price": "12.00",
        "sku": "4355103686722-tee-wom-robl-l",
        "inventoryPolicy": "DENY",
        "inventoryItem": { "tracked": false },
        "options": [ "Women", "L", "Royal Blue"],
        "weight": 0.3125,
        "weightUnit": "POUNDS",
        "requiresShipping": true,
        "imageSrc": "https://cdn.shopify.com/s/files/1/1869/0319/products/artwork_2FokNRdYBimVwcz1D9Mqol-R7EzcKd9ftUycaF9kz6a-uVf7CLkzDgl9b9IjbZuD-color-none.png?v=1573687790"
      },
      {
        "title": "Women / XL / Royal Blue",
        "price": "12.00",
        "sku": "4355103686722-tee-wom-robl-xl",
        "inventoryPolicy": "DENY",
        "inventoryItem": { "tracked": false },
        "options": [ "Women", "XL", "Royal Blue"],
        "weight": 0.3525,
        "weightUnit": "POUNDS",
        "requiresShipping": true,
        "imageSrc": "https://cdn.shopify.com/s/files/1/1869/0319/products/artwork_2FokNRdYBimVwcz1D9Mqol-R7EzcKd9ftUycaF9kz6a-uVf7CLkzDgl9b9IjbZuD-color-none.png?v=1573687790"
      },
      {
        "title": "Women / 2XL / Royal Blue",
        "price": "13.00",
        "sku": "4355103686722-tee-wom-robl-2xl",
        "inventoryPolicy": "DENY",
        "inventoryItem": { "tracked": false },
        "options": [ "Women", "2XL", "Royal Blue"],
        "weight": 0.3725,
        "weightUnit": "POUNDS",
        "requiresShipping": true,
        "imageSrc": "https://cdn.shopify.com/s/files/1/1869/0319/products/artwork_2FokNRdYBimVwcz1D9Mqol-R7EzcKd9ftUycaF9kz6a-uVf7CLkzDgl9b9IjbZuD-color-none.png?v=1573687790"
      },
      {
        "title": "Women / 3XL / Royal Blue",
        "price": "14.00",
        "sku": "4355103686722-tee-wom-robl-3xl",
        "inventoryPolicy": "DENY",
        "inventoryItem": { "tracked": false },
        "options": [ "Women", "3XL", "Royal Blue"],
        "weight": 0.4025,
        "weightUnit": "POUNDS",
        "requiresShipping": true,
        "imageSrc": "https://cdn.shopify.com/s/files/1/1869/0319/products/artwork_2FokNRdYBimVwcz1D9Mqol-R7EzcKd9ftUycaF9kz6a-uVf7CLkzDgl9b9IjbZuD-color-none.png?v=1573687790"
      },
      {
        "title": "Womens Fitted / S / Black",
        "price": "12.00",
        "sku": "4355103686722-tee-wofi-bla-s",
        "inventoryPolicy": "DENY",
        "inventoryItem": { "tracked": false },
        "options": [ "Womens Fitted", "S", "Black"],
        "weight": 0.2525,
        "weightUnit": "POUNDS",
        "requiresShipping": true,
        "imageSrc": "https://cdn.shopify.com/s/files/1/1869/0319/products/artwork_2FokNRdYBimVwcz1D9Mqol-R7EzcKd9ftUycaF9kz6a-uVf7CLkzDgl9b9IjbZuD-color-none.png?v=1573687790"
      },
      {
        "title": "Womens Fitted / M / Black",
        "price": "12.00",
        "sku": "4355103686722-tee-wofi-bla-m",
        "inventoryPolicy": "DENY",
        "inventoryItem": { "tracked": false },
        "options": [ "Womens Fitted", "M", "Black"],
        "weight": 0.2725,
        "weightUnit": "POUNDS",
        "requiresShipping": true,
        "imageSrc": "https://cdn.shopify.com/s/files/1/1869/0319/products/artwork_2FokNRdYBimVwcz1D9Mqol-R7EzcKd9ftUycaF9kz6a-uVf7CLkzDgl9b9IjbZuD-color-none.png?v=1573687790"
      },
      {
        "title": "Womens Fitted / L / Black",
        "price": "12.00",
        "sku": "4355103686722-tee-wofi-bla-l",
        "inventoryPolicy": "DENY",
        "inventoryItem": { "tracked": false },
        "options": [ "Womens Fitted", "L", "Black"],
        "weight": 0.3125,
        "weightUnit": "POUNDS",
        "requiresShipping": true,
        "imageSrc": "https://cdn.shopify.com/s/files/1/1869/0319/products/artwork_2FokNRdYBimVwcz1D9Mqol-R7EzcKd9ftUycaF9kz6a-uVf7CLkzDgl9b9IjbZuD-color-none.png?v=1573687790"
      },
      {
        "title": "Womens Fitted / XL / Black",
        "price": "12.00",
        "sku": "4355103686722-tee-wofi-bla-xl",
        "inventoryPolicy": "DENY",
        "inventoryItem": { "tracked": false },
        "options": [ "Womens Fitted", "XL", "Black"],
        "weight": 0.3525,
        "weightUnit": "POUNDS",
        "requiresShipping": true,
        "imageSrc": "https://cdn.shopify.com/s/files/1/1869/0319/products/artwork_2FokNRdYBimVwcz1D9Mqol-R7EzcKd9ftUycaF9kz6a-uVf7CLkzDgl9b9IjbZuD-color-none.png?v=1573687790"
      },
      {
        "title": "Womens Fitted / 2XL / Black",
        "price": "13.00",
        "sku": "4355103686722-tee-wofi-bla-2xl",
        "inventoryPolicy": "DENY",
        "inventoryItem": { "tracked": false },
        "options": [ "Womens Fitted", "2XL", "Black"],
        "weight": 0.3725,
        "weightUnit": "POUNDS",
        "requiresShipping": true,
        "imageSrc": "https://cdn.shopify.com/s/files/1/1869/0319/products/artwork_2FokNRdYBimVwcz1D9Mqol-R7EzcKd9ftUycaF9kz6a-uVf7CLkzDgl9b9IjbZuD-color-none.png?v=1573687790"
      },
      {
        "title": "Womens Fitted / S / Royal Blue",
        "price": "12.00",
        "sku": "4355103686722-tee-wofi-robl-s",
        "inventoryPolicy": "DENY",
        "inventoryItem": { "tracked": false },
        "options": [ "Womens Fitted", "S", "Royal Blue"],
        "weight": 0.2525,
        "weightUnit": "POUNDS",
        "requiresShipping": true,
        "imageSrc": "https://cdn.shopify.com/s/files/1/1869/0319/products/artwork_2FokNRdYBimVwcz1D9Mqol-R7EzcKd9ftUycaF9kz6a-uVf7CLkzDgl9b9IjbZuD-color-none.png?v=1573687790"
      },
      {
        "title": "Womens Fitted / M / Royal Blue",
        "price": "12.00",
        "sku": "4355103686722-tee-wofi-robl-m",
        "inventoryPolicy": "DENY",
        "inventoryItem": { "tracked": false },
        "options": [ "Womens Fitted", "M", "Royal Blue"],
        "weight": 0.2725,
        "weightUnit": "POUNDS",
        "requiresShipping": true,
        "imageSrc": "https://cdn.shopify.com/s/files/1/1869/0319/products/artwork_2FokNRdYBimVwcz1D9Mqol-R7EzcKd9ftUycaF9kz6a-uVf7CLkzDgl9b9IjbZuD-color-none.png?v=1573687790"
      },
      {
        "title": "Womens Fitted / L / Royal Blue",
        "price": "12.00",
        "sku": "4355103686722-tee-wofi-robl-l",
        "inventoryPolicy": "DENY",
        "inventoryItem": { "tracked": false },
        "options": [ "Womens Fitted", "L", "Royal Blue"],
        "weight": 0.3125,
        "weightUnit": "POUNDS",
        "requiresShipping": true,
        "imageSrc": "https://cdn.shopify.com/s/files/1/1869/0319/products/artwork_2FokNRdYBimVwcz1D9Mqol-R7EzcKd9ftUycaF9kz6a-uVf7CLkzDgl9b9IjbZuD-color-none.png?v=1573687790"
      },
      {
        "title": "Womens Fitted / XL / Royal Blue",
        "price": "12.00",
        "sku": "4355103686722-tee-wofi-robl-xl",
        "inventoryPolicy": "DENY",
        "inventoryItem": { "tracked": false },
        "options": [ "Womens Fitted", "XL", "Royal Blue"],
        "weight": 0.3525,
        "weightUnit": "POUNDS",
        "requiresShipping": true,
        "imageSrc": "https://cdn.shopify.com/s/files/1/1869/0319/products/artwork_2FokNRdYBimVwcz1D9Mqol-R7EzcKd9ftUycaF9kz6a-uVf7CLkzDgl9b9IjbZuD-color-none.png?v=1573687790"
      },
      {
        "title": "Womens Fitted / 2XL / Royal Blue",
        "price": "13.00",
        "sku": "4355103686722-tee-wofi-robl-2xl",
        "inventoryPolicy": "DENY",
        "inventoryItem": { "tracked": false },
        "options": [ "Womens Fitted", "2XL", "Royal Blue"],
        "weight": 0.3725,
        "weightUnit": "POUNDS",
        "requiresShipping": true,
        "imageSrc": "https://cdn.shopify.com/s/files/1/1869/0319/products/artwork_2FokNRdYBimVwcz1D9Mqol-R7EzcKd9ftUycaF9kz6a-uVf7CLkzDgl9b9IjbZuD-color-none.png?v=1573687790"
      },
      {
        "title": "Youth / XS / Black",
        "price": "12.00",
        "sku": "4355103686722-tee-you-bla-xs",
        "inventoryPolicy": "DENY",
        "inventoryItem": { "tracked": false },
        "options": [ "Youth", "XS", "Black"],
        "weight": 0.2525,
        "weightUnit": "POUNDS",
        "requiresShipping": true,
        "imageSrc": "https://cdn.shopify.com/s/files/1/1869/0319/products/artwork_2FokNRdYBimVwcz1D9Mqol-R7EzcKd9ftUycaF9kz6a-uVf7CLkzDgl9b9IjbZuD-color-none.png?v=1573687790"
      },
      {
        "title": "Youth / S / Black",
        "price": "12.00",
        "sku": "4355103686722-tee-you-bla-s",
        "inventoryPolicy": "DENY",
        "inventoryItem": { "tracked": false },
        "options": [ "Youth", "S", "Black"],
        "weight": 0.2725,
        "weightUnit": "POUNDS",
        "requiresShipping": true,
        "imageSrc": "https://cdn.shopify.com/s/files/1/1869/0319/products/artwork_2FokNRdYBimVwcz1D9Mqol-R7EzcKd9ftUycaF9kz6a-uVf7CLkzDgl9b9IjbZuD-color-none.png?v=1573687790"
      },
      {
        "title": "Youth / M / Black",
        "price": "12.00",
        "sku": "4355103686722-tee-you-bla-m",
        "inventoryPolicy": "DENY",
        "inventoryItem": { "tracked": false },
        "options": [ "Youth", "M", "Black"],
        "weight": 0.3125,
        "weightUnit": "POUNDS",
        "requiresShipping": true,
        "imageSrc": "https://cdn.shopify.com/s/files/1/1869/0319/products/artwork_2FokNRdYBimVwcz1D9Mqol-R7EzcKd9ftUycaF9kz6a-uVf7CLkzDgl9b9IjbZuD-color-none.png?v=1573687790"
      },
      {
        "title": "Youth / L / Black",
        "price": "12.00",
        "sku": "4355103686722-tee-you-bla-l",
        "inventoryPolicy": "DENY",
        "inventoryItem": { "tracked": false },
        "options": [ "Youth", "L", "Black"],
        "weight": 0.3625,
        "weightUnit": "POUNDS",
        "requiresShipping": true,
        "imageSrc": "https://cdn.shopify.com/s/files/1/1869/0319/products/artwork_2FokNRdYBimVwcz1D9Mqol-R7EzcKd9ftUycaF9kz6a-uVf7CLkzDgl9b9IjbZuD-color-none.png?v=1573687790"
      },
      {
        "title": "Youth / XL / Black",
        "price": "12.00",
        "sku": "4355103686722-tee-you-bla-xl",
        "inventoryPolicy": "DENY",
        "inventoryItem": { "tracked": false },
        "options": [ "Youth", "XL", "Black"],
        "weight": 0.4063,
        "weightUnit": "POUNDS",
        "requiresShipping": true,
        "imageSrc": "https://cdn.shopify.com/s/files/1/1869/0319/products/artwork_2FokNRdYBimVwcz1D9Mqol-R7EzcKd9ftUycaF9kz6a-uVf7CLkzDgl9b9IjbZuD-color-none.png?v=1573687790"
      },
      {
        "title": "Youth / XS / Royal Blue",
        "price": "12.00",
        "sku": "4355103686722-tee-you-robl-xs",
        "inventoryPolicy": "DENY",
        "inventoryItem": { "tracked": false },
        "options": [ "Youth", "XS", "Royal Blue"],
        "weight": 0.2525,
        "weightUnit": "POUNDS",
        "requiresShipping": true,
        "imageSrc": "https://cdn.shopify.com/s/files/1/1869/0319/products/artwork_2FokNRdYBimVwcz1D9Mqol-R7EzcKd9ftUycaF9kz6a-uVf7CLkzDgl9b9IjbZuD-color-none.png?v=1573687790"
      },
      {
        "title": "Youth / S / Royal Blue",
        "price": "12.00",
        "sku": "4355103686722-tee-you-robl-s",
        "inventoryPolicy": "DENY",
        "inventoryItem": { "tracked": false },
        "options": [ "Youth", "S", "Royal Blue"],
        "weight": 0.2725,
        "weightUnit": "POUNDS",
        "requiresShipping": true,
        "imageSrc": "https://cdn.shopify.com/s/files/1/1869/0319/products/artwork_2FokNRdYBimVwcz1D9Mqol-R7EzcKd9ftUycaF9kz6a-uVf7CLkzDgl9b9IjbZuD-color-none.png?v=1573687790"
      },
      {
        "title": "Youth / M / Royal Blue",
        "price": "12.00",
        "sku": "4355103686722-tee-you-robl-m",
        "inventoryPolicy": "DENY",
        "inventoryItem": { "tracked": false },
        "options": [ "Youth", "M", "Royal Blue"],
        "weight": 0.3125,
        "weightUnit": "POUNDS",
        "requiresShipping": true,
        "imageSrc": "https://cdn.shopify.com/s/files/1/1869/0319/products/artwork_2FokNRdYBimVwcz1D9Mqol-R7EzcKd9ftUycaF9kz6a-uVf7CLkzDgl9b9IjbZuD-color-none.png?v=1573687790"
      },
      {
        "title": "Youth / L / Royal Blue",
        "price": "12.00",
        "sku": "4355103686722-tee-you-robl-l",
        "inventoryPolicy": "DENY",
        "inventoryItem": { "tracked": false },
        "options": [ "Youth", "L", "Royal Blue"],
        "weight": 0.3625,
        "weightUnit": "POUNDS",
        "requiresShipping": true,
        "imageSrc": "https://cdn.shopify.com/s/files/1/1869/0319/products/artwork_2FokNRdYBimVwcz1D9Mqol-R7EzcKd9ftUycaF9kz6a-uVf7CLkzDgl9b9IjbZuD-color-none.png?v=1573687790"
      },
      {
        "title": "Youth / XL / Royal Blue",
        "price": "12.00",
        "sku": "4355103686722-tee-you-robl-xl",
        "inventoryPolicy": "DENY",
        "inventoryItem": { "tracked": false },
        "options": [ "Youth", "XL", "Royal Blue"],
        "weight": 0.4063,
        "weightUnit": "POUNDS",
        "requiresShipping": true,
        "imageSrc": "https://cdn.shopify.com/s/files/1/1869/0319/products/artwork_2FokNRdYBimVwcz1D9Mqol-R7EzcKd9ftUycaF9kz6a-uVf7CLkzDgl9b9IjbZuD-color-none.png?v=1573687790"
      }
    ]
  }
}
